pdf_scout/__init__.py
pdf_scout/app.py
pdf_scout/bookmarks.py
pdf_scout/cache.py
pdf_scout/custom_types.py
pdf_scout/extract.py
pdf_scout/logger.py
pdf_scout/paragraphs.py
pdf_scout/scoring.py
pdf_scout/utils.py
pdf_scout-0.0.6.dist-info/entry_points.txt
pdf_scout-0.0.6.dist-info/WHEEL
pdf_scout-0.0.6.dist-info/METADATA
pdf_scout-0.0.6.dist-info/RECORD
