Metadata-Version: 2.1
Name: pdf-scout
Version: 0.0.6
Summary: automatically create bookmarks in a PDF file
Home-page: https://github.com/hueyy/pdf_scout
License: EUPL-1.2
Keywords: pdf,bookmark,outline
Author: Huey
Author-email: hello@huey.xyz
Requires-Python: >=3.10,<4.0
Classifier: License :: OSI Approved :: European Union Public Licence 1.2 (EUPL 1.2)
Classifier: Programming Language :: Python :: 3
Classifier: Programming Language :: Python :: 3.10
Classifier: Programming Language :: Python :: 3.11
Requires-Dist: joblib (>=1.2.0,<2.0.0)
Requires-Dist: pdfplumber (>=0.7.6,<0.8.0)
Requires-Dist: pypdf (>=3.1.0,<4.0.0)
Requires-Dist: rich (>=12.5.1,<13.0.0)
Requires-Dist: typer[all] (>=0.6.1,<0.7.0)
Requires-Dist: unidecode (>=1.3.6,<2.0.0)
Project-URL: Documentation, https://github.com/hueyy/pdf_scout
Project-URL: Repository, https://github.com/hueyy/pdf_scout
